odoo/addons/product_search_category_attribute_sale/README.rst
odoo/addons/product_search_category_attribute_sale/__init__.py
odoo/addons/product_search_category_attribute_sale/__manifest__.py
odoo/addons/product_search_category_attribute_sale/i18n/es.po
odoo/addons/product_search_category_attribute_sale/readme/CONTRIBUTORS.md
odoo/addons/product_search_category_attribute_sale/readme/DESCRIPTION.md
odoo/addons/product_search_category_attribute_sale/readme/USAGE.md
odoo/addons/product_search_category_attribute_sale/security/ir.model.access.csv
odoo/addons/product_search_category_attribute_sale/static/description/icon.png
odoo/addons/product_search_category_attribute_sale/static/description/index.html
odoo/addons/product_search_category_attribute_sale/tests/__init__.py
odoo/addons/product_search_category_attribute_sale/tests/test_product_search_category_attr_sales.py
odoo/addons/product_search_category_attribute_sale/views/sale_order_views.xml
odoo/addons/product_search_category_attribute_sale/wizards/__init__.py
odoo/addons/product_search_category_attribute_sale/wizards/product_search_cat_attr_line_sale.py
odoo/addons/product_search_category_attribute_sale/wizards/product_search_cat_attr_sale.py
odoo/addons/product_search_category_attribute_sale/wizards/product_search_category_attribute_views.xml
odoo/addons/product_search_category_attribute_sale/wizards/product_search_category_sale_product_line.py
odoo/addons/product_search_category_attribute_sale/wizards/sale_order.py
odoo_addon_product_search_category_attribute_sale-16.0.1.0.0.1.dist-info/METADATA
odoo_addon_product_search_category_attribute_sale-16.0.1.0.0.1.dist-info/WHEEL
odoo_addon_product_search_category_attribute_sale-16.0.1.0.0.1.dist-info/top_level.txt
odoo_addon_product_search_category_attribute_sale-16.0.1.0.0.1.dist-info/RECORD
